tigersyn/__init__.py
tigersyn/syn.py
tigersyn/syn_tool.py
tigersyn-0.0.5.dist-info/LICENSE
tigersyn-0.0.5.dist-info/METADATA
tigersyn-0.0.5.dist-info/WHEEL
tigersyn-0.0.5.dist-info/top_level.txt
tigersyn-0.0.5.dist-info/RECORD
