Metadata-Version: 2.1
Name: tigersyn
Version: 0.0.5
Summary: Processing MRI images based on deep-learning
Home-page: https://github.com/StanleyWangTW/tigersyn
Author: X. S. Wang
Author-email: 
License: UNKNOWN
Platform: UNKNOWN
Classifier: Intended Audience :: Developers
Classifier: Programming Language :: Python :: 3.9
Classifier: License :: OSI Approved :: MIT License
Classifier: Operating System :: Microsoft :: Windows
Requires-Python: >=3.9
License-File: LICENSE
Requires-Dist: numpy
Requires-Dist: nibabel
Requires-Dist: nilearn
Requires-Dist: onnxruntime
